{"type":"Scene","props":{"width":750,"height":1334},"compId":2,"child":[{"type":"Sprite","props":{"y":0,"x":0,"texture":"res/game/MainBg.png","scaleX":1,"name":"MainBg"},"compId":3,"child":[{"type":"Script","props":{"topPanel":"@node:31","testerror":"@node:343","minter":"@Prefab:res/TestPre.prefab","jiqiren2":"@node:415","jiqiren1":"@node:414","ShopPanel":"@node:48","MyPanel":"@node:101","LoadingPanel":"@node:387","InvitationPanel":"@node:327","BuildingPanel":"@node:345","BindinggFailePanel":"@node:373","runtime":"game/GameMgr.js"},"compId":17},{"type":"Sprite","props":{"y":367,"x":138,"texture":"res/game/zhongjjian.png","name":"Center"},"compId":409},{"type":"Sprite","props":{"y":1173,"x":308,"texture":"res/ani/jiqiren/jiqiren1.png","name":"jiqiren1"},"compId":414},{"type":"Sprite","props":{"y":808,"x":7,"texture":"res/ani/jiqiren/jiqiren2.png","name":"jiqiren2"},"compId":415},{"type":"Sprite","props":{"y":266,"x":625,"visible":false,"texture":"res/ui/MaskBg.png","name":"StartPos1"},"compId":410},{"type":"Sprite","props":{"y":324,"x":491,"visible":false,"texture":"res/ui/MaskBg.png","name":"EndPos1"},"compId":411},{"type":"Sprite","props":{"y":177,"x":443,"visible":false,"texture":"res/ui/MaskBg.png","name":"StartPos2"},"compId":412},{"type":"Sprite","props":{"y":214,"x":615,"visible":false,"texture":"res/ui/MaskBg.png","name":"EndPos2"},"compId":413}]},{"type":"Panel","props":{"y":0,"x":0,"width":750,"name":"TopPanel","height":72},"compId":31,"child":[{"type":"Button","props":{"y":44,"x":160,"width":0,"toggle":false,"stateNum":1,"skin":"res/ui/mainPanel/shouye-jinbi@3x.png","selected":false,"pivotY":44,"pivotX":160,"name":"AddCoinBtn","labelStrokeColor":"#ffffff","labelSize":40,"labelFont":"SimHei","labelColors":"#ffffff","labelBold":false,"labelAlign":"center","label":"1232K","height":0},"compId":32,"child":[{"type":"Sprite","props":{"y":19.5,"x":198,"texture":"res/ui/mainPanel/CoinAdd.png"},"compId":33},{"type":"Script","props":{"runtime":"ui/AddCoinBtn.js"},"compId":35}]}]},{"type":"Panel","props":{"y":1208,"x":0,"width":750,"name":"BottomPanel","height":132},"compId":36,"child":[{"type":"Sprite","props":{"y":34,"x":11.5,"texture":"res/ui/mainPanel/shouye-diban.png","name":"BottomPanelBg"},"compId":51},{"type":"Button","props":{"y":61,"x":130,"width":122,"toggle":false,"stateNum":1,"skin":"res/ui/mainPanel/shouye-fangkuai@3x.png","selected":false,"pivotY":61,"pivotX":61,"name":"ShopBtn","labelSize":25,"labelPadding":"20","labelFont":"SimHei","labelColors":"#3AD6E3","labelBold":false,"labelAlign":"center","label":"Shop","height":122},"compId":37,"child":[{"type":"Image","props":{"y":7,"x":30,"visible":true,"skin":"res/ui/mainPanel/shouye-anniu1.png","name":"normal"},"compId":52},{"type":"Image","props":{"y":7,"x":30,"skin":"res/ui/mainPanel/shouye-anniu1select.png","name":"select"},"compId":69},{"type":"Script","props":{"y":0,"x":0,"selectedImg":"@node:69","normalImg":"@node:52","runtime":"ui/UIButton.js"},"compId":60}]},{"type":"Button","props":{"y":61,"x":297,"width":122,"toggle":false,"stateNum":1,"skin":"res/ui/mainPanel/shouye-fangkuai@3x.png","selected":false,"pivotY":61,"pivotX":61,"name":"TeamBtn","labelStrokeColor":"#ffffff","labelSize":25,"labelPadding":"20","labelFont":"SimHei","labelColors":"#ffffff","labelBold":false,"labelAlign":"center","label":"Team","height":122},"compId":40,"child":[{"type":"Image","props":{"y":7,"x":30,"skin":"res/ui/mainPanel/shouye-anniu2.png","name":"normal"},"compId":54},{"type":"Image","props":{"y":7,"x":30,"skin":"res/ui/mainPanel/shouye-anniu2select.png","name":"select"},"compId":67},{"type":"Script","props":{"y":0,"x":0,"selectedImg":"@node:67","normalImg":"@node:54","runtime":"ui/UIButton.js"},"compId":59}]},{"type":"Button","props":{"y":62,"x":456,"width":122,"toggle":false,"stateNum":1,"skin":"res/ui/mainPanel/shouye-fangkuai@3x.png","selected":false,"pivotY":61,"pivotX":61,"name":"RepairBtn","labelStrokeColor":"#ffffff","labelSize":25,"labelPadding":"20","labelFont":"SimHei","labelColors":"#ffffff","labelBold":false,"labelAlign":"center","label":"Repair","height":122},"compId":41,"child":[{"type":"Image","props":{"y":7,"x":30,"skin":"res/ui/mainPanel/shouye-anniu3.png","name":"normal"},"compId":55},{"type":"Image","props":{"y":14,"x":30,"skin":"res/ui/mainPanel/shouye-anniu3select.png","name":"select"},"compId":66},{"type":"Script","props":{"y":0,"x":0,"selectedImg":"@node:66","normalImg":"@node:55","runtime":"ui/UIButton.js"},"compId":61}]},{"type":"Button","props":{"y":61,"x":617,"width":122,"toggle":false,"stateNum":1,"skin":"res/ui/mainPanel/shouye-fangkuai@3x.png","selected":false,"pivotY":61,"pivotX":61,"name":"MeBtn","labelStrokeColor":"#ffffff","labelSize":25,"labelPadding":"20","labelFont":"SimHei","labelColors":"#ffffff","labelBold":false,"labelAlign":"center","label":"Me","height":122},"compId":42,"child":[{"type":"Image","props":{"y":7,"x":30,"skin":"res/ui/mainPanel/shouye-anniu4.png","name":"normal"},"compId":56},{"type":"Image","props":{"y":7,"x":30,"skin":"res/ui/mainPanel/shouye-anniu4select.png","name":"select"},"compId":64},{"type":"Script","props":{"selectedImg":"@node:64","normalImg":"@node:56","runtime":"ui/UIButton.js"},"compId":62}]},{"type":"Script","props":{"TeamDialog":"@node:159","ShopDialog":"@node:48","RepairDialog":"@node:238","MeDialog":"@node:101","runtime":"ui/BottomPanel.js"},"compId":58}]},{"type":"Dialog","props":{"y":0,"x":0,"width":750,"visible":false,"pivotX":0,"name":"ShopPanel","height":1334},"compId":48,"child":[{"type":"Image","props":{"y":0,"x":0,"width":750,"visible":true,"skin":"res/ui/MaskBg.png","sizeGrid":"8,8,8,8","name":"MaskBg","height":1334},"compId":372},{"type":"Image","props":{"y":285,"x":-4,"skin":"res/ui/shopPanel/dabiankuang.png","name":"Bg","sizeGrid":"143,0,100,0"},"compId":49},{"type":"Image","props":{"y":514,"x":22,"width":710,"skin":"res/ui/rankPanel/RankListBg.png","name":"CotentBg","height":772},"compId":313},{"type":"Box","props":{"y":420,"x":0,"width":744,"name":"ShopToggle","height":118,"anchorY":0,"anchorX":0},"compId":79,"child":[{"type":"Image","props":{"y":0,"x":0,"visible":false,"skin":"res/ui/shopPanel/daohang-weixuanzhong.png","name":"ToggleNormal"},"compId":84},{"type":"Image","props":{"y":0,"x":0,"visible":false,"skin":"res/ui/shopPanel/daohang-xuanzhong.png","name":"ToggleSelect"},"compId":85},{"type":"Button","props":{"y":1.5,"x":38,"toggle":false,"stateNum":1,"skin":"res/ui/shopPanel/daohang-weixuanzhong.png","name":"TagGoldBtn","labelSize":30,"labelFont":"SimHei","labelColors":"#B3C7D7 ","label":"GoldMiner"},"compId":75},{"type":"Button","props":{"y":2,"x":268,"toggle":false,"stateNum":1,"skin":"res/ui/shopPanel/daohang-weixuanzhong.png","name":"TagSliverBtn","labelSize":30,"labelFont":"SimHei","labelColors":"#B3C7D7 ","label":"SliverMiner"},"compId":77},{"type":"Button","props":{"y":2,"x":498,"toggle":false,"stateNum":1,"skin":"res/ui/shopPanel/daohang-weixuanzhong.png","name":"TagCoinBtn","labelSize":30,"labelFont":"SimHei","labelColors":"#B3C7D7 ","label":"Coins"},"compId":76},{"type":"Script","props":{"toggleSliverBtn":"@node:77","toggleSelectedImg":"@node:85","toggleNornalImg":"@node:84","toggleGoldBtn":"@node:75","toggleCoinBtn":"@node:76","tagGoldBtn":"@node:75","shopList":"@node:86","runtime":"ui/ShopPanel/ShopToggle.js"},"compId":83},{"type":"List","props":{"y":87,"x":8,"width":734,"spaceY":5,"repeatY":1,"repeatX":1,"name":"ShopList","height":770,"elasticEnabled":true},"compId":86,"child":[{"type":"Box","props":{"y":28,"x":24,"width":693,"renderType":"render","name":"Item","height":284},"compId":90,"child":[{"type":"Image","props":{"y":-0.5,"x":-0.5,"skin":"res/ui/shopPanel/diban-xuanzhong.png","name":"ItemBg","sizeGrid":"37,47,51,38"},"compId":87},{"type":"Image","props":{"y":41.5,"x":31.5,"skin":"res/ui/shopPanel/shangpinbeijng_pink.png","name":"ItemIconFrame"},"compId":89},{"type":"Image","props":{"skin":"res/ui/shopPanel/kuangji_blue.png","name":"ItemIcon","centerY":-3,"centerX":-220},"compId":88},{"type":"Label","props":{"y":60,"x":240,"width":342,"text":"yellow miner","name":"MinerName","height":40,"fontSize":34,"font":"SimHei","color":"#FBA623","bold":true,"align":"left"},"compId":91},{"type":"Label","props":{"y":111,"x":240,"width":427,"underline":false,"text":"ETHG is a completely independent chain\\ngame platform, which is safe transparent\\nand decentralized.","name":"MinerDes","italic":false,"height":79,"fontSize":22,"font":"SimHei","color":"#B0C4DF ","bold":false,"align":"left"},"compId":93},{"type":"Button","props":{"y":221,"x":534,"width":197,"stateNum":1,"skin":"res/ui/shopPanel/button-buy.png","pivotY":32,"pivotX":99,"name":"ItemBuyBtn","labelSize":30,"labelFont":"SimHei","labelColors":"#ffffff","labelBold":true,"label":"Buy","height":63},"compId":98},{"type":"Label","props":{"y":195,"x":240,"width":203,"text":"100 ETH","name":"MinerPrice","height":40,"fontSize":34,"font":"SimHei","color":"#FFFFFF ","bold":true,"align":"left"},"compId":127},{"type":"Script","props":{"itemBtn":"@node:98","runtime":"ui/ShopPanel/ShopItem.js"},"compId":129},{"type":"Label","props":{"y":61,"x":240,"width":203,"text":"100 Coins","name":"gold_txt","height":36,"fontSize":34,"font":"SimHei","color":"#FBA623","bold":true,"align":"left"},"compId":423}]},{"type":"Script","props":{"runtime":"ui/ShopPanel/ShopList.js"},"compId":99}]}]},{"type":"Button","props":{"y":276,"x":636,"stateNum":1,"skin":"res/ui/shopPanel/guanbi.png","name":"close"},"compId":416}]},{"type":"Dialog","props":{"y":0,"x":0,"width":750,"visible":false,"pivotX":0,"name":"MyPanel","height":1334},"compId":101,"child":[{"type":"Image","props":{"y":0,"x":0,"width":750,"visible":true,"skin":"res/ui/MaskBg.png","sizeGrid":"8,8,8,8","name":"MaskBg","height":1334},"compId":371},{"type":"Image","props":{"y":285,"x":-4,"skin":"res/ui/shopPanel/dabiankuang.png","name":"Bg","sizeGrid":"143,0,100,0"},"compId":102},{"type":"Image","props":{"y":514,"x":22,"width":710,"skin":"res/ui/rankPanel/RankListBg.png","name":"CotentBg","height":772},"compId":312},{"type":"Box","props":{"y":420,"x":0,"width":744,"name":"MyPanelToggle","height":118,"anchorY":0,"anchorX":0},"compId":104,"child":[{"type":"Image","props":{"y":0,"x":0,"visible":false,"skin":"res/ui/shopPanel/daohang-weixuanzhong.png","name":"ToggleNormal"},"compId":105},{"type":"Image","props":{"y":0,"x":0,"visible":false,"skin":"res/ui/shopPanel/daohang-xuanzhong.png","name":"ToggleSelect"},"compId":106},{"type":"Button","props":{"y":1.5,"x":38,"toggle":false,"stateNum":1,"skin":"res/ui/shopPanel/daohang-weixuanzhong.png","name":"MyMinerBtn","labelSize":30,"labelFont":"SimHei","labelColors":"#B3C7D7 ","label":"My Miners"},"compId":107},{"type":"Button","props":{"y":2,"x":268,"toggle":false,"stateNum":1,"skin":"res/ui/shopPanel/daohang-weixuanzhong.png","name":"MyHomeBtn","labelSize":30,"labelFont":"SimHei","labelColors":"#B3C7D7 ","label":"My Home"},"compId":108},{"type":"List","props":{"y":87,"x":8,"width":734,"var":"ShopList","spaceY":5,"repeatY":1,"repeatX":1,"name":"ShopList","height":770,"elasticEnabled":true},"compId":111,"child":[{"type":"Box","props":{"y":30,"x":22,"renderType":"render","name":"Item"},"compId":112,"child":[{"type":"Image","props":{"y":-0.5,"x":-0.5,"skin":"res/ui/shopPanel/diban-xuanzhong.png","name":"ItemBg","sizeGrid":"37,47,51,38"},"compId":113},{"type":"Image","props":{"y":41.5,"x":31.5,"var":"ItemIconFrame","skin":"res/ui/shopPanel/shangpinbeijng_pink.png","name":"ItemIconFrame"},"compId":114},{"type":"Image","props":{"y":67.25,"x":64.5,"var":"ItemIcon","skin":"res/ui/shopPanel/kuangji_blue.png","name":"ItemIcon"},"compId":115},{"type":"Label","props":{"y":60,"x":250,"width":342,"var":"MinerName","text":"yellow miner","name":"MinerName","height":40,"fontSize":36,"font":"SimHei","color":"#FBA623","bold":true,"align":"left"},"compId":116},{"type":"Label","props":{"y":110,"x":251,"width":170,"text":"Total Revenue:","height":25,"fontSize":24,"font":"SimHei","color":"#B0C4DF ","bold":false,"align":"left"},"compId":117},{"type":"Label","props":{"y":110,"x":426,"width":270,"var":"MinerTotalRevenue","text":"10000000000eth","name":"MinerTotalRevenue","height":25,"fontSize":24,"font":"SimHei","color":"#B0C4DF ","bold":false,"align":"left"},"compId":118},{"type":"Label","props":{"y":150,"x":251,"width":170,"text":"Extracted:","height":25,"fontSize":24,"font":"SimHei","color":"#B0C4DF ","bold":false,"align":"left"},"compId":119},{"type":"Label","props":{"y":150,"x":382,"width":170,"text":"1.00","name":"MinerExtracted","height":25,"fontSize":24,"font":"SimHei","color":"#B0C4DF ","bold":false,"align":"left"},"compId":120},{"type":"Label","props":{"y":190,"x":250,"width":170,"text":"Total Days:","height":25,"fontSize":24,"font":"SimHei","color":"#B0C4DF ","bold":false,"align":"left"},"compId":121},{"type":"Label","props":{"y":190,"x":394,"width":170,"text":"1.00","name":"MinerTotalDays","height":25,"fontSize":24,"font":"SimHei","color":"#B0C4DF ","bold":false,"align":"left"},"compId":122},{"type":"Button","props":{"y":177,"x":469,"stateNum":1,"skin":"res/ui/shopPanel/button-buy.png","name":"ReceiveBuy","labelSize":30,"labelFont":"SimHei","labelColors":"#ffffff","labelBold":true,"label":"Receive"},"compId":123,"child":[{"type":"Script","props":{"runtime":"ui/UIButton.js"},"compId":124}]}]}]},{"type":"Script","props":{"y":1,"x":0,"toggleSelectedImg":"@node:106","toggleNornalImg":"@node:105","shopList":"@node:111","myHomeItem":"@node:283","MyMinerBtn":"@node:107","MyHomeBtn":"@node:108","runtime":"ui/MyPanel/MyPanelTogle.js"},"compId":126},{"type":"Box","props":{"y":107,"x":27,"width":687,"renderType":"render","name":"MyHomeItem","height":606},"compId":283,"child":[{"type":"Image","props":{"y":11,"x":8,"width":678,"skin":"res/ui/shopPanel/diban-xuanzhong.png","name":"ItemBg","height":184,"sizeGrid":"37,47,51,38"},"compId":284},{"type":"Image","props":{"y":52,"x":38,"skin":"res/ui/rankPanel/RankIconFrame.png","name":"ItemIconFrame"},"compId":285,"child":[{"type":"Image","props":{"y":-4,"x":-3,"skin":"res/ui/rankPanel/touxiang1.png","name":"ItemIcon"},"compId":286}]},{"type":"Button","props":{"y":96,"x":544,"width":165,"stateNum":1,"skin":"res/ui/MyPanel/button-Copy.png","scaleY":1,"scaleX":1,"pivotY":27,"pivotX":83,"name":"ModifyNameBtn","labelSize":30,"labelFont":"SimHei","labelColors":"#ffffff","labelBold":true,"label":"Modify","height":53},"compId":294,"child":[{"type":"Script","props":{"runtime":"ui/UIButton.js"},"compId":295}]},{"type":"TextInput","props":{"y":68,"x":138,"width":282,"text":"Your Name","skin":"res/ui/MyPanel/input.png","padding":"0","overflow":"visible","name":"PlayerName","leading":0,"height":52,"fontSize":26,"font":"SimHei","color":"#29364F","bold":true,"align":"center"},"compId":296},{"type":"Image","props":{"y":211,"x":9,"width":678,"skin":"res/ui/shopPanel/diban-xuanzhong.png","name":"ItemBg02","height":184,"sizeGrid":"37,47,51,38"},"compId":297,"child":[{"type":"Image","props":{"y":37,"x":27,"skin":"res/ui/MyPanel/Wallet.png","name":"ItemIcon"},"compId":301}]},{"type":"Button","props":{"y":347,"x":544,"width":165,"stateNum":1,"skin":"res/ui/MyPanel/button-Copy.png","scaleY":1,"scaleX":1,"pivotY":27,"pivotX":83,"name":"CopyAddressBtn","labelSize":30,"labelFont":"SimHei","labelColors":"#ffffff","labelBold":true,"label":"Copy","height":53},"compId":299,"child":[{"type":"Script","props":{"runtime":"ui/UIButton.js"},"compId":302}]},{"type":"Label","props":{"y":279,"x":133,"width":505,"underline":false,"text":"0x177e01e1344e57C0680b5a126267Fe9AFc9274f0","name":"MinerAddress","italic":false,"height":24,"fontSize":22,"font":"SimHei","color":"#B0C4DF","bold":false,"align":"left"},"compId":309},{"type":"Button","props":{"y":347,"x":325,"width":165,"stateNum":1,"skin":"res/ui/MyPanel/button-Logout.png","pivotY":27,"pivotX":83,"name":"LogoutBtn","labelSize":30,"labelFont":"SimHei","labelColors":"#ffffff","labelBold":true,"label":"Log out","height":54},"compId":310,"child":[{"type":"Script","props":{"runtime":"ui/UIButton.js"},"compId":311}]}]}]},{"type":"Button","props":{"y":276,"x":636,"stateNum":1,"skin":"res/ui/shopPanel/guanbi.png","name":"close"},"compId":417}]},{"type":"Dialog","props":{"y":0,"x":0,"width":750,"visible":false,"pivotX":0,"name":"RankPanel","height":1334},"compId":159,"child":[{"type":"Image","props":{"y":0,"x":0,"width":750,"visible":true,"skin":"res/ui/MaskBg.png","sizeGrid":"8,8,8,8","name":"MaskBg","height":1334},"compId":370},{"type":"Image","props":{"y":285,"x":-4,"skin":"res/ui/shopPanel/dabiankuang.png","name":"Bg","sizeGrid":"143,0,100,0"},"compId":160},{"type":"Image","props":{"y":389,"x":20,"skin":"res/ui/rankPanel/TopBg.png","name":"TopCotent"},"compId":180,"child":[{"type":"Image","props":{"y":21,"x":10,"width":688,"skin":"res/ui/rankPanel/BottomBg.png","name":"ETHBg","height":65},"compId":185,"child":[{"type":"Image","props":{"y":7.5,"x":15,"skin":"res/ui/rankPanel/ETH.png","name":"ETH"},"compId":183},{"type":"Label","props":{"y":19,"x":84,"width":209,"text":"Total reward ETH：","height":27,"fontSize":24,"font":"SimHei","color":"#B0C4DF "},"compId":187},{"type":"Label","props":{"y":19,"x":336,"width":145,"text":"100","name":"ETHVaule","height":27,"fontSize":24,"font":"SimHei","color":"#B0C4DF "},"compId":188},{"type":"Label","props":{"y":22,"x":566,"text":"Receive","name":"ReceiveETH","fontSize":24,"font":"SimHei","color":"#05F3FF"},"compId":190}]},{"type":"Image","props":{"y":91,"x":10,"width":688,"skin":"res/ui/rankPanel/BottomBg.png","name":"CoinBg","height":65},"compId":184,"child":[{"type":"Image","props":{"y":7.5,"x":14,"skin":"res/ui/rankPanel/Coin.png","name":"Coin"},"compId":182},{"type":"Label","props":{"y":19,"x":84,"width":209,"text":"Total reward coin：","height":27,"fontSize":24,"font":"SimHei","color":"#B0C4DF "},"compId":186},{"type":"Label","props":{"y":19,"x":336,"width":145,"text":"200","name":"CoinValue","height":27,"fontSize":24,"font":"SimHei","color":"#B0C4DF "},"compId":189},{"type":"Label","props":{"y":22,"x":566,"text":"Receive","name":"ReceiveCoin","fontSize":24,"font":"SimHei","color":"#05F3FF"},"compId":191}]}]},{"type":"Box","props":{"y":587,"x":10,"width":740,"name":"RankToggle","height":118,"anchorY":0,"anchorX":0},"compId":162,"child":[{"type":"Image","props":{"y":0,"x":0,"visible":false,"skin":"res/ui/shopPanel/daohang-weixuanzhong.png","name":"ToggleNormal"},"compId":163},{"type":"Image","props":{"y":0,"x":0,"visible":false,"skin":"res/ui/shopPanel/daohang-xuanzhong.png","name":"ToggleSelect"},"compId":164},{"type":"Button","props":{"y":1.5,"x":25,"toggle":false,"stateNum":1,"skin":"res/ui/shopPanel/daohang-xuanzhong.png","name":"TagKingBtn","labelSize":35,"labelFont":"SimHei","labelColors":"#B3C7D7 ","label":"King"},"compId":165},{"type":"Button","props":{"y":2,"x":255,"toggle":false,"stateNum":1,"skin":"res/ui/shopPanel/daohang-weixuanzhong.png","name":"TagDemeanorBtn","labelSize":35,"labelFont":"SimHei","labelColors":"#B3C7D7 ","label":"Demeanor"},"compId":166},{"type":"Button","props":{"y":2,"x":485,"toggle":false,"stateNum":1,"skin":"res/ui/shopPanel/daohang-weixuanzhong.png","name":"TagEliteBtn","labelSize":35,"labelFont":"SimHei","labelColors":"#B3C7D7 ","label":"Elite"},"compId":167},{"type":"Image","props":{"y":92,"x":14,"skin":"res/ui/rankPanel/RankListBg.png","name":"RankListBg"},"compId":192},{"type":"Label","props":{"y":121,"x":33,"width":390,"var":"type_txt","text":"Demeanor:","name":"type_txt","height":33,"fontSize":26,"color":"#D9992A","bold":true,"align":"left"},"compId":198},{"type":"Label","props":{"y":122,"x":170,"width":234,"var":"KingValue","text":"1000000","name":"KingValue","height":33,"fontSize":26,"color":"#D9992A","bold":true,"align":"left"},"compId":199},{"type":"List","props":{"y":91,"x":11,"width":716,"spaceY":5,"repeatY":2,"repeatX":1,"name":"RankList","height":558,"elasticEnabled":true},"compId":169,"child":[{"type":"Box","props":{"y":73,"x":19,"width":682,"renderType":"render","name":"Item","height":111},"compId":170,"child":[{"type":"Image","props":{"y":1,"x":-3,"skin":"res/ui/rankPanel/BottomBg.png","name":"ItemBg"},"compId":171},{"type":"Image","props":{"y":14,"x":22,"skin":"res/ui/rankPanel/RankIconFrame.png","name":"ItemFrame"},"compId":193},{"type":"Image","props":{"y":11,"x":18,"skin":"res/ui/rankPanel/touxiang1.png","name":"ItemIcon"},"compId":173},{"type":"Script","props":{"y":-3,"x":0,"itemBtn":"@node:98","enabled":false,"runtime":"ui/ShopPanel/ShopItem.js"},"compId":178},{"type":"Label","props":{"y":49,"x":120,"width":429,"underline":false,"text":"0x177e01e1344e57C0680b5a126267Fe9AFc9274f0","name":"MinerAddress1","italic":false,"height":26,"fontSize":22,"font":"SimHei","color":"#B0C4DF","bold":false,"align":"left"},"compId":427},{"type":"Label","props":{"y":47,"x":368,"width":117,"underline":false,"text":"Gold Miner","name":"MinerType1","italic":false,"height":28,"fontSize":22,"font":"SimHei","color":"#F7CE73","bold":false,"align":"left"},"compId":428},{"type":"Image","props":{"y":50,"x":515,"skin":"res/ui/rankPanel/CoinIcon.png","name":"CoinIcon1"},"compId":429},{"type":"Label","props":{"y":51,"x":552,"width":85,"text":"100","name":"CoinCount1","height":29,"fontSize":22,"font":"SimHei","color":"#D1942D","bold":true,"align":"left"},"compId":430},{"type":"Label","props":{"y":30,"x":148,"width":429,"underline":false,"text":"0x177e01e1344e57C0680b5a126267Fe9AFc9274f0","name":"MinerAddress","italic":false,"height":26,"fontSize":20,"font":"SimHei","color":"#B0C4DF","bold":false,"align":"left"},"compId":194},{"type":"Label","props":{"y":63,"x":148,"width":117,"underline":false,"text":"Gold Miner","name":"MinerType","italic":false,"height":28,"fontSize":22,"font":"SimHei","color":"#F7CE73","bold":false,"align":"left"},"compId":175},{"type":"Image","props":{"y":62,"x":481,"skin":"res/ui/rankPanel/CoinIcon.png","name":"CoinIcon"},"compId":196},{"type":"Label","props":{"y":63,"x":518,"width":85,"text":"100","name":"CoinCount","height":29,"fontSize":20,"font":"SimHei","color":"#D1942D","bold":true,"align":"left"},"compId":197},{"type":"Label","props":{"y":63,"x":357,"width":86,"text":"100","name":"ETHCount","height":25,"fontSize":20,"font":"SimHei","color":"#26B7FC","bold":true,"align":"left"},"compId":177},{"type":"Image","props":{"y":53,"x":318,"skin":"res/ui/rankPanel/EthIcon.png","scaleY":1,"scaleX":1,"name":"EthIcon"},"compId":195}]}]},{"type":"Script","props":{"type_txt":"@node:198","toggleSelectedImg":"@node:164","toggleNornalImg":"@node:163","rankList":"@node:169","coinValue":"@node:189","TagKingBtn":"@node:165","TagEliteBtn":"@node:167","TagDemeanorBtn":"@node:166","KingValue":"@node:199","ETHVaule":"@node:188","runtime":"ui/RankPanel/RankToggle.js"},"compId":201}]},{"type":"Button","props":{"y":276,"x":636,"stateNum":1,"skin":"res/ui/shopPanel/guanbi.png","name":"close"},"compId":418},{"type":"Script","props":{"topCotent":"@node:180","coinValue":"@node:189","ReceiveETH":"@node:190","ReceiveCoin":"@node:191","ETHVaule":"@node:188","CoinValue":"@node:189","runtime":"ui/RankPanel/RankPanel.js"},"compId":424}]},{"type":"Dialog","props":{"y":0,"x":0,"width":750,"visible":false,"pivotX":0,"name":"RepairPanel","height":1334},"compId":238,"child":[{"type":"Image","props":{"y":0,"x":0,"width":750,"visible":true,"skin":"res/ui/MaskBg.png","sizeGrid":"8,8,8,8","name":"MaskBg","height":1334},"compId":369},{"type":"Image","props":{"y":285,"x":-4,"skin":"res/ui/shopPanel/dabiankuang.png","name":"Bg","sizeGrid":"143,0,100,0"},"compId":239},{"type":"List","props":{"y":391,"x":8,"width":734,"spaceY":5,"repeatY":1,"repeatX":1,"name":"ShopList","height":773,"elasticEnabled":true},"compId":246,"child":[{"type":"Box","props":{"y":34,"x":19,"width":717,"renderType":"render","name":"Item","height":283},"compId":247,"child":[{"type":"Image","props":{"y":-0.5,"x":-0.5,"skin":"res/ui/shopPanel/diban-xuanzhong.png","name":"ItemBg","sizeGrid":"37,47,51,38"},"compId":248},{"type":"Image","props":{"y":41.5,"x":31.5,"skin":"res/ui/shopPanel/shangpinbeijng_pink.png","name":"ItemIconFrame"},"compId":249},{"type":"Image","props":{"y":67.25,"x":64.5,"skin":"res/ui/shopPanel/kuangji_blue.png","name":"ItemIcon"},"compId":250},{"type":"Label","props":{"y":123,"x":239,"width":427,"underline":false,"text":"ETHG is a completely independent chain\\ngame platform, which is safe transparent\\nand decentralized.","name":"MinerDes","italic":false,"height":79,"fontSize":22,"font":"SimHei","color":"#B0C4DF ","bold":false,"align":"left"},"compId":261},{"type":"Label","props":{"y":73.5,"x":241,"width":342,"text":"yellow miner","name":"MinerName","height":40,"fontSize":36,"font":"SimHei","color":"#FBA623","bold":true,"align":"left"},"compId":251},{"type":"Button","props":{"y":216,"x":568,"width":197,"stateNum":1,"skin":"res/ui/shopPanel/button-buy.png","pivotY":32,"pivotX":99,"name":"ItemRepairBtn","labelSize":30,"labelFont":"SimHei","labelColors":"#ffffff","labelBold":true,"label":"Repair","height":63},"compId":258,"child":[{"type":"Script","props":{"runtime":"ui/UIButton.js"},"compId":259}]},{"type":"Label","props":{"y":201,"x":239,"width":427,"underline":false,"text":"......","name":"daojishi_txt","italic":false,"height":67,"fontSize":22,"font":"SimHei","color":"#B0C4DF ","bold":false,"align":"left"},"compId":435}]}]},{"type":"Button","props":{"y":276,"x":636,"stateNum":1,"skin":"res/ui/shopPanel/guanbi.png","name":"close"},"compId":419},{"type":"Script","props":{"shopList":"@node:246","repairItemPanel":"@node:262","runtime":"ui/RepairPanel/RepairPanel.js"},"compId":422}]},{"type":"Dialog","props":{"y":0,"x":0,"width":750,"visible":false,"pivotX":0,"name":"RepairItemPanel","height":1334},"compId":262,"child":[{"type":"Image","props":{"y":0,"x":0,"width":750,"visible":true,"skin":"res/ui/MaskBg.png","sizeGrid":"8,8,8,8","name":"MaskBg","height":1334},"compId":368},{"type":"Image","props":{"y":285,"x":-4,"skin":"res/ui/shopPanel/dabiankuang.png","name":"Bg","sizeGrid":"143,0,100,0"},"compId":263},{"type":"Button","props":{"y":275,"x":632,"stateNum":1,"skin":"res/ui/shopPanel/guanbi.png","name":"close"},"compId":274},{"type":"Image","props":{"y":398,"x":19,"skin":"res/ui/RepairItemPanel/repairBg.png","name":"RepairBg"},"compId":276},{"type":"Image","props":{"y":560,"x":162.5,"skin":"res/ui/RepairItemPanel/card.png","name":"RepairCardBg"},"compId":277},{"type":"Image","props":{"y":651,"x":242,"skin":"res/ui/shopPanel/kuangji_blue.png","scaleY":2,"scaleX":2,"name":"RepairCard"},"compId":278},{"type":"Button","props":{"y":1174,"x":376,"stateNum":1,"skin":"res/ui/RepairItemPanel/button-Repair.png","name":"RepairBtn","labelSize":34,"labelPadding":"0","labelFont":"SimHei","labelColors":"#FFFFFF","labelAlign":"center","label":"Repair","anchorY":0.5,"anchorX":0.5},"compId":279},{"type":"Label","props":{"y":1108,"x":316,"width":140,"text":"cost:      coin","name":"CostLabel","height":25,"fontSize":24,"color":"#05F3FF"},"compId":280},{"type":"Label","props":{"y":1108,"x":375,"width":59,"text":"50","name":"CostValue","height":25,"fontSize":24,"color":"#05F3FF"},"compId":281},{"type":"Label","props":{"y":491,"x":170,"width":411,"valign":"top","text":"Gold Miner","name":"MinerName2","height":33,"fontSize":28,"font":"SimHei","color":"#D9992A","bold":true,"align":"center"},"compId":282}]},{"type":"Dialog","props":{"y":0,"x":-1,"width":750,"visible":false,"pivotX":0,"name":"InvitationPanel","height":1334},"compId":327,"child":[{"type":"Image","props":{"y":0,"x":0,"width":750,"visible":true,"skin":"res/ui/MaskBg.png","sizeGrid":"8,8,8,8","name":"MaskBg","height":1334},"compId":367},{"type":"Image","props":{"y":285,"x":-4,"width":758,"skin":"res/ui/shopPanel/dabiankuang.png","name":"Bg","height":608,"sizeGrid":"143,0,100,0"},"compId":328},{"type":"TextInput","props":{"y":522,"x":30,"width":689,"type":"text","skin":"res/ui/shopPanel/diban-xuanzhong.png","prompt":"轻输入邀请人地址","name":"InputAddress","height":135,"fontSize":26,"color":"#B0C4DF","bold":true,"align":"center","sizeGrid":"37,47,51,38"},"compId":342},{"type":"Label","props":{"y":448,"x":40,"width":669,"text":"Fill in the inviter's wallet address","name":"Tip","height":40,"fontSize":36,"font":"SimHei","color":"#B0C4DF","bold":true,"align":"left"},"compId":336},{"type":"Button","props":{"y":734,"x":361,"width":197,"stateNum":1,"skin":"res/ui/shopPanel/button-buy.png","pivotY":32,"pivotX":99,"name":"InvitationBtn","labelSize":30,"labelFont":"SimHei","labelColors":"#ffffff","labelBold":true,"label":"Confirm","height":63},"compId":337,"child":[{"type":"Script","props":{"runtime":"ui/UIButton.js"},"compId":338}]},{"type":"Image","props":{"y":659,"x":62,"skin":"res/ui/InvitationPanel/jinggao.png","name":"ErrorTip"},"compId":343,"child":[{"type":"Label","props":{"y":1,"x":39,"width":143,"text":"Error Address!","name":"Error","height":18,"fontSize":20,"font":"SimHei","color":"#FF0000"},"compId":344}]},{"type":"Button","props":{"y":276,"x":632,"stateNum":1,"skin":"res/ui/InvitationPanel/fanhui.png","name":"close"},"compId":362}]},{"type":"Dialog","props":{"y":0,"x":0,"width":750,"visible":false,"pivotX":0,"name":"BuildingPanel","isShowEffect":true,"isPopupCenter":true,"height":1334,"autoDestroyAtClosed":false},"compId":345,"child":[{"type":"Image","props":{"y":0,"x":0,"width":750,"visible":true,"skin":"res/ui/MaskBg.png","sizeGrid":"8,8,8,8","name":"MaskBg","mouseThrough":true,"mouseEnabled":true,"height":1334},"compId":365},{"type":"Image","props":{"y":560,"x":5,"skin":"res/ui/BuildingPanel/bushu.png","name":"Bg"},"compId":346},{"type":"Label","props":{"y":588,"x":108.5,"width":533,"text":"Mining machine is being deployed","name":"Tip","height":40,"fontSize":32,"font":"SimHei","color":"#D9992A","bold":true,"align":"left"},"compId":349},{"type":"ProgressBar","props":{"y":667,"x":72,"value":0.8,"skin":"res/ui/BuildingPanel/MyProgress.png","name":"progress"},"compId":358}]},{"type":"Dialog","props":{"y":0,"x":0,"width":750,"visible":false,"pivotX":0,"name":"BindinggFailePanel","isShowEffect":true,"isPopupCenter":true,"height":1334,"autoDestroyAtClosed":false},"compId":373,"child":[{"type":"Image","props":{"y":0,"x":0,"width":750,"visible":true,"skin":"res/ui/MaskBg.png","sizeGrid":"8,8,8,8","name":"MaskBg","height":1334},"compId":374},{"type":"Image","props":{"y":560,"x":5,"skin":"res/ui/BuildingPanel/bushu.png","name":"Bg"},"compId":375},{"type":"Label","props":{"y":588,"x":108.5,"width":533,"text":"Wrong address","name":"Tip","height":40,"fontSize":32,"font":"SimHei","color":"#D9992A","bold":true,"align":"center"},"compId":376},{"type":"Label","props":{"y":685,"x":31.5,"width":692,"text":"Please fill in the correct inviter's wallet address","name":"TipDEs","height":40,"fontSize":26,"font":"SimHei","color":"#B0C4DF","bold":true,"align":"center"},"compId":378},{"type":"Button","props":{"y":836,"x":357,"width":197,"stateNum":1,"skin":"res/ui/shopPanel/button-buy.png","pivotY":32,"pivotX":99,"name":"close","labelSize":30,"labelFont":"SimHei","labelColors":"#ffffff","labelBold":true,"label":"CONFIRM","height":63},"compId":379}]},{"type":"Dialog","props":{"y":0,"x":0,"width":750,"visible":false,"pivotX":0,"name":"LoadingPanel","isShowEffect":true,"isPopupCenter":true,"height":1334,"autoDestroyAtClosed":false},"compId":387,"child":[{"type":"Image","props":{"y":0,"x":0,"skin":"res/ui/LoadPanel/image-bj.png","name":"Bg"},"compId":389,"child":[{"type":"Image","props":{"y":0,"x":0,"skin":"res/ui/LoadPanel/image-shang.png","name":"DecTop"},"compId":396},{"type":"Image","props":{"y":1293,"x":0,"skin":"res/ui/LoadPanel/image-xia.png","name":"DecBottom"},"compId":397}]},{"type":"Image","props":{"y":628,"x":0,"skin":"res/ui/LoadPanel/image-fangxing.png","name":"PlatformBg"},"compId":393,"child":[{"type":"Image","props":{"y":-284,"x":0,"skin":"res/ui/LoadPanel/image-faguang-hou.png","name":"DecBg"},"compId":394},{"type":"Image","props":{"y":-172,"x":-2,"skin":"res/ui/LoadPanel/image-faguang-qian.png","name":"DecFg"},"compId":395}]},{"type":"Image","props":{"y":1258,"x":103,"skin":"res/ui/LoadPanel/image-kuang.png","name":"CheckBox"},"compId":402,"child":[{"type":"Button","props":{"y":32,"x":99,"stateNum":1,"skin":"res/ui/LoadPanel/image-kuang.png","pivotY":32,"pivotX":99,"name":"commitBtn","labelSize":30,"labelFont":"SimHei","labelColors":"#ffffff","labelBold":true},"compId":392},{"type":"Image","props":{"visible":false,"skin":"res/ui/LoadPanel/image-duihao.png","name":"commitImage"},"compId":405},{"type":"Label","props":{"y":4,"x":40,"width":345,"text":"I have read and accepeted the","name":"TipDEs","height":30,"fontSize":22,"font":"SimHei","color":"#B0C4DF","bold":true,"align":"center"},"compId":391},{"type":"Label","props":{"y":4,"x":385,"width":187,"text":"Terms of Service","name":"TipService","height":30,"fontSize":22,"font":"SimHei","color":"#D9992A","bold":true,"align":"center"},"compId":390},{"type":"Label","props":{"y":-344,"x":99,"width":345,"visible":true,"var":"tishi_txt","text":"1","name":"tishi_txt","height":84,"fontSize":45,"font":"SimHei","color":"#ffffff","bold":true,"align":"center"},"compId":436}]},{"type":"Script","props":{"tishi_txt":"@node:436","TipService":"@node:390","LoadBtn":"@node:408","CommitBtn":"@node:392","runtime":"ui/LoadingPanel/LoadingPanel.js"},"compId":406},{"type":"Button","props":{"y":1226,"x":375,"width":197,"stateNum":1,"skin":"res/ui/RepairItemPanel/button-Repair.png","pivotY":32,"pivotX":99,"name":"LoadBtn","labelSize":28,"labelFont":"SimHei","labelColors":"#ffffff","labelBold":true,"label":"Load","height":64},"compId":408}]},{"type":"Script","props":{"runtime":"game/NetManager.js"},"compId":420}],"animations":[{"nodes":[{"target":410,"keyframes":{"y":[{"value":266,"tweenMethod":"linearNone","tween":true,"target":410,"key":"y","index":0},{"value":273.15,"tweenMethod":"linearNone","tween":true,"target":410,"key":"y","index":3},{"value":331,"tweenMethod":"linearNone","tween":true,"target":410,"key":"y","index":45}],"x":[{"value":625,"tweenMethod":"linearNone","tween":true,"target":410,"key":"x","index":0},{"value":620,"tweenMethod":"linearNone","tween":true,"target":410,"key":"x","index":3},{"value":487,"tweenMethod":"linearNone","tween":true,"target":410,"key":"x","index":45}]}}],"name":"ani1","id":1,"frameRate":24,"action":0}],"loadList":["res/game/MainBg.png","res/TestPre.prefab","res/game/zhongjjian.png","res/ani/jiqiren/jiqiren1.png","res/ani/jiqiren/jiqiren2.png","res/ui/MaskBg.png","res/ui/mainPanel/shouye-jinbi@3x.png","res/ui/mainPanel/CoinAdd.png","res/ui/mainPanel/shouye-diban.png","res/ui/mainPanel/shouye-fangkuai@3x.png","res/ui/mainPanel/shouye-anniu1.png","res/ui/mainPanel/shouye-anniu1select.png","res/ui/mainPanel/shouye-anniu2.png","res/ui/mainPanel/shouye-anniu2select.png","res/ui/mainPanel/shouye-anniu3.png","res/ui/mainPanel/shouye-anniu3select.png","res/ui/mainPanel/shouye-anniu4.png","res/ui/mainPanel/shouye-anniu4select.png","res/ui/shopPanel/dabiankuang.png","res/ui/rankPanel/RankListBg.png","res/ui/shopPanel/daohang-weixuanzhong.png","res/ui/shopPanel/daohang-xuanzhong.png","res/ui/shopPanel/diban-xuanzhong.png","res/ui/shopPanel/shangpinbeijng_pink.png","res/ui/shopPanel/kuangji_blue.png","res/ui/shopPanel/button-buy.png","res/ui/shopPanel/guanbi.png","res/ui/rankPanel/RankIconFrame.png","res/ui/rankPanel/touxiang1.png","res/ui/MyPanel/button-Copy.png","res/ui/MyPanel/input.png","res/ui/MyPanel/Wallet.png","res/ui/MyPanel/button-Logout.png","res/ui/rankPanel/TopBg.png","res/ui/rankPanel/BottomBg.png","res/ui/rankPanel/ETH.png","res/ui/rankPanel/Coin.png","res/ui/rankPanel/CoinIcon.png","res/ui/rankPanel/EthIcon.png","res/ui/RepairItemPanel/repairBg.png","res/ui/RepairItemPanel/card.png","res/ui/RepairItemPanel/button-Repair.png","res/ui/InvitationPanel/jinggao.png","res/ui/InvitationPanel/fanhui.png","res/ui/BuildingPanel/bushu.png","res/ui/BuildingPanel/MyProgress.png","res/ui/LoadPanel/image-bj.png","res/ui/LoadPanel/image-shang.png","res/ui/LoadPanel/image-xia.png","res/ui/LoadPanel/image-fangxing.png","res/ui/LoadPanel/image-faguang-hou.png","res/ui/LoadPanel/image-faguang-qian.png","res/ui/LoadPanel/image-kuang.png","res/ui/LoadPanel/image-duihao.png"],"loadList3D":[]}